[
  {
    "timestamp": "2026-05-23T18:24:07.469144",
    "n_symbols": 47,
    "timeframes": [
      "4h",
      "1d"
    ],
    "elapsed": 26.7,
    "total_raw": 127,
    "total_approved": 14,
    "results": [
      {
        "strategy": "Wammie (Double Bottom)",
        "signal": "LONG",
        "price": 39.43,
        "zone": 38.71242,
        "first_touch": 38.68686,
        "second_touch": 38.7,
        "candles_between": 80,
        "score": 8,
        "entry": 39.43,
        "stop_loss": 38.518857,
        "take_profit": 41.942988,
        "rr_ratio": 2.76,
        "details": "Wammie | Zona=38.7124 | 1º=38.6869 2º=38.7 (80 candles) | Score=8/10 | R:R=1:2.76",
        "symbol": "ITUB4.SA",
        "display_name": "ITUB4 (Itaú)",
        "timeframe": "1d"
      },
      {
        "strategy": "Wammie (Double Bottom)",
        "signal": "LONG",
        "price": 17.62,
        "zone": 17.39137,
        "first_touch": 17.39452,
        "second_touch": 17.47,
        "candles_between": 93,
        "score": 8,
        "entry": 17.620001,
        "stop_loss": 17.304417,
        "take_profit": 18.305981,
        "rr_ratio": 2.17,
        "details": "Wammie | Zona=17.3914 | 1º=17.3945 2º=17.47 (93 candles) | Score=8/10 | R:R=1:2.17",
        "symbol": "BBDC4.SA",
        "display_name": "BBDC4 (Bradesco)",
        "timeframe": "1d"
      },
      {
        "strategy": "Last Kiss",
        "signal": "SHORT",
        "price": 17.62,
        "zone": 17.84488,
        "score": 8,
        "entry": 17.620001,
        "stop_loss": 17.9341,
        "take_profit": 16.976478,
        "rr_ratio": 2.05,
        "details": "Last Kiss Bearish | Zona=17.8449 | Score=8/10 | R:R=1:2.05",
        "symbol": "BBDC4.SA",
        "display_name": "BBDC4 (Bradesco)",
        "timeframe": "1d"
      },
      {
        "strategy": "Last Kiss",
        "signal": "SHORT",
        "price": 75329.21875,
        "zone": 76043.06641,
        "score": 8,
        "entry": 75329.21875,
        "stop_loss": 76423.281738,
        "take_profit": 72676.007812,
        "rr_ratio": 2.43,
        "details": "Last Kiss Bearish | Zona=76043.0664 | Score=8/10 | R:R=1:2.43",
        "symbol": "BTC-USD",
        "display_name": "Bitcoin (BTC/USD)",
        "timeframe": "4h"
      },
      {
        "strategy": "Kangaroo Tail",
        "signal": "LONG",
        "price": 75329.21875,
        "zone": 73918.23438,
        "tail": 74306.71875,
        "room_to_left": 32,
        "score": 10,
        "entry": 75329.21875,
        "stop_loss": 73548.643203,
        "take_profit": 79387.229167,
        "rr_ratio": 2.28,
        "details": "Bullish Kangaroo Tail | Zona=73918.2344 | Tail=74306.7188 | 32 candles sem toque | Score=10/10 | R:R=1:2.28",
        "symbol": "BTC-USD",
        "display_name": "Bitcoin (BTC/USD)",
        "timeframe": "1d"
      },
      {
        "strategy": "Kangaroo Tail",
        "signal": "LONG",
        "price": 2058.72998,
        "zone": 2022.95862,
        "tail": 2020.36316,
        "room_to_left": 47,
        "score": 8,
        "entry": 2058.72998,
        "stop_loss": 2012.843825,
        "take_profit": 2170.995483,
        "rr_ratio": 2.45,
        "details": "Bullish Kangaroo Tail | Zona=2022.9586 | Tail=2020.3632 | 47 candles sem toque | Score=8/10 | R:R=1:2.45",
        "symbol": "ETH-USD",
        "display_name": "Ethereum (ETH/USD)",
        "timeframe": "1d"
      },
      {
        "strategy": "Wammie (Double Bottom)",
        "signal": "LONG",
        "price": 2058.72998,
        "zone": 2078.61621,
        "first_touch": 2061.46753,
        "second_touch": 2078.61621,
        "candles_between": 41,
        "score": 8,
        "entry": 2058.72998,
        "stop_loss": 2020.363159,
        "take_profit": 2149.282959,
        "rr_ratio": 2.36,
        "details": "Wammie | Zona=2078.6162 | 1º=2061.4675 2º=2078.6162 (41 candles) | Score=8/10 | R:R=1:2.36",
        "symbol": "ETH-USD",
        "display_name": "Ethereum (ETH/USD)",
        "timeframe": "1d"
      },
      {
        "strategy": "Last Kiss",
        "signal": "SHORT",
        "price": 1.34329,
        "zone": 1.34734,
        "score": 9,
        "entry": 1.343292,
        "stop_loss": 1.354075,
        "take_profit": 1.319023,
        "rr_ratio": 2.25,
        "details": "Last Kiss Bearish | Zona=1.3473 | Score=9/10 | R:R=1:2.25",
        "symbol": "GBPUSD=X",
        "display_name": "GBP/USD",
        "timeframe": "4h"
      },
      {
        "strategy": "Last Kiss",
        "signal": "SHORT",
        "price": 0.71296,
        "zone": 0.7137,
        "score": 8,
        "entry": 0.712962,
        "stop_loss": 0.717264,
        "take_profit": 0.701592,
        "rr_ratio": 2.64,
        "details": "Last Kiss Bearish | Zona=0.7137 | Score=8/10 | R:R=1:2.64",
        "symbol": "AUDUSD=X",
        "display_name": "AUD/USD",
        "timeframe": "4h"
      },
      {
        "strategy": "Last Kiss",
        "signal": "SHORT",
        "price": 0.98399,
        "zone": 0.98802,
        "score": 8,
        "entry": 0.98399,
        "stop_loss": 0.992961,
        "take_profit": 0.963134,
        "rr_ratio": 2.32,
        "details": "Last Kiss Bearish | Zona=0.988 | Score=8/10 | R:R=1:2.32",
        "symbol": "AUDCAD=X",
        "display_name": "AUD/CAD",
        "timeframe": "4h"
      },
      {
        "strategy": "Moolah (Double Top)",
        "signal": "SHORT",
        "price": 1.05397,
        "zone": 1.0428,
        "first_touch": 1.05132,
        "second_touch": 1.05066,
        "candles_between": 42,
        "score": 8,
        "entry": 1.05397,
        "stop_loss": 1.0567,
        "take_profit": 1.0428,
        "rr_ratio": 4.09,
        "details": "Moolah | Zona=1.0428 | 1º=1.0513 2º=1.0507 (42 candles) | Score=8/10 | R:R=1:4.09",
        "symbol": "GBPCHF=X",
        "display_name": "GBP/CHF",
        "timeframe": "1d"
      },
      {
        "strategy": "EMA Pullback",
        "signal": "LONG",
        "rsi": 49.47,
        "price": 93.115,
        "ema21": 93.191,
        "ema50": 92.987,
        "score": 8,
        "entry": 93.114998,
        "stop_loss": 92.725046,
        "take_profit": 93.939334,
        "rr_ratio": 2.11,
        "details": "Pullback para EMA21 (0.1%) em uptrend | Score=8/10 | R:R=1:2.11",
        "symbol": "NZDJPY=X",
        "display_name": "NZD/JPY",
        "timeframe": "1d"
      },
      {
        "strategy": "Last Kiss",
        "signal": "SHORT",
        "price": 2.907,
        "zone": 2.9225,
        "score": 8,
        "entry": 2.907,
        "stop_loss": 3.01,
        "take_profit": 2.676,
        "rr_ratio": 2.24,
        "details": "Last Kiss Bearish | Zona=2.9225 | Score=8/10 | R:R=1:2.24",
        "symbol": "NG=F",
        "display_name": "Gás Natural",
        "timeframe": "1d"
      },
      {
        "strategy": "Last Kiss",
        "signal": "SHORT",
        "price": 10466.25977,
        "zone": 10480.17505,
        "score": 8,
        "entry": 10466.259766,
        "stop_loss": 10532.575924,
        "take_profit": 10286.945312,
        "rr_ratio": 2.7,
        "details": "Last Kiss Bearish | Zona=10480.175 | Score=8/10 | R:R=1:2.7",
        "symbol": "^FTSE",
        "display_name": "FTSE 100 (UK100)",
        "timeframe": "4h"
      }
    ]
  },
  {
    "timestamp": "2026-05-24T00:23:40.479582",
    "n_symbols": 47,
    "timeframes": [
      "4h",
      "1d"
    ],
    "elapsed": 35.7,
    "total_raw": 126,
    "total_approved": 12,
    "results": [
      {
        "strategy": "Wammie (Double Bottom)",
        "signal": "LONG",
        "price": 39.43,
        "zone": 38.71242,
        "first_touch": 38.68686,
        "second_touch": 38.7,
        "candles_between": 80,
        "score": 8,
        "entry": 39.43,
        "stop_loss": 38.518859,
        "take_profit": 41.94299,
        "rr_ratio": 2.76,
        "details": "Wammie | Zona=38.7124 | 1º=38.6869 2º=38.7 (80 candles) | Score=8/10 | R:R=1:2.76",
        "symbol": "ITUB4.SA",
        "display_name": "ITUB4 (Itaú)",
        "timeframe": "1d"
      },
      {
        "strategy": "Wammie (Double Bottom)",
        "signal": "LONG",
        "price": 17.62,
        "zone": 17.39137,
        "first_touch": 17.39452,
        "second_touch": 17.47,
        "candles_between": 93,
        "score": 8,
        "entry": 17.620001,
        "stop_loss": 17.304416,
        "take_profit": 18.305981,
        "rr_ratio": 2.17,
        "details": "Wammie | Zona=17.3914 | 1º=17.3945 2º=17.47 (93 candles) | Score=8/10 | R:R=1:2.17",
        "symbol": "BBDC4.SA",
        "display_name": "BBDC4 (Bradesco)",
        "timeframe": "1d"
      },
      {
        "strategy": "Last Kiss",
        "signal": "SHORT",
        "price": 17.62,
        "zone": 17.84487,
        "score": 8,
        "entry": 17.620001,
        "stop_loss": 17.934097,
        "take_profit": 16.97648,
        "rr_ratio": 2.05,
        "details": "Last Kiss Bearish | Zona=17.8449 | Score=8/10 | R:R=1:2.05",
        "symbol": "BBDC4.SA",
        "display_name": "BBDC4 (Bradesco)",
        "timeframe": "1d"
      },
      {
        "strategy": "Wammie (Double Bottom)",
        "signal": "LONG",
        "price": 76570.9375,
        "zone": 74958.57031,
        "first_touch": 75318.98438,
        "second_touch": 75323.875,
        "candles_between": 22,
        "score": 9,
        "entry": 76570.9375,
        "stop_loss": 74306.71875,
        "take_profit": 82005.960938,
        "rr_ratio": 2.4,
        "details": "Wammie | Zona=74958.5703 | 1º=75318.9844 2º=75323.875 (22 candles) | Score=9/10 | R:R=1:2.4",
        "symbol": "BTC-USD",
        "display_name": "Bitcoin (BTC/USD)",
        "timeframe": "1d"
      },
      {
        "strategy": "Wammie (Double Bottom)",
        "signal": "LONG",
        "price": 2115.52002,
        "zone": 2078.61621,
        "first_touch": 2061.46753,
        "second_touch": 2078.61621,
        "candles_between": 41,
        "score": 8,
        "entry": 2115.52002,
        "stop_loss": 2020.363159,
        "take_profit": 2382.865234,
        "rr_ratio": 2.81,
        "details": "Wammie | Zona=2078.6162 | 1º=2061.4675 2º=2078.6162 (41 candles) | Score=8/10 | R:R=1:2.81",
        "symbol": "ETH-USD",
        "display_name": "Ethereum (ETH/USD)",
        "timeframe": "1d"
      },
      {
        "strategy": "Last Kiss",
        "signal": "SHORT",
        "price": 1.34329,
        "zone": 1.34734,
        "score": 9,
        "entry": 1.343292,
        "stop_loss": 1.354075,
        "take_profit": 1.319023,
        "rr_ratio": 2.25,
        "details": "Last Kiss Bearish | Zona=1.3473 | Score=9/10 | R:R=1:2.25",
        "symbol": "GBPUSD=X",
        "display_name": "GBP/USD",
        "timeframe": "4h"
      },
      {
        "strategy": "Last Kiss",
        "signal": "SHORT",
        "price": 0.71296,
        "zone": 0.7137,
        "score": 8,
        "entry": 0.712962,
        "stop_loss": 0.717264,
        "take_profit": 0.701592,
        "rr_ratio": 2.64,
        "details": "Last Kiss Bearish | Zona=0.7137 | Score=8/10 | R:R=1:2.64",
        "symbol": "AUDUSD=X",
        "display_name": "AUD/USD",
        "timeframe": "4h"
      },
      {
        "strategy": "Last Kiss",
        "signal": "SHORT",
        "price": 0.98399,
        "zone": 0.98802,
        "score": 8,
        "entry": 0.98399,
        "stop_loss": 0.992961,
        "take_profit": 0.963134,
        "rr_ratio": 2.32,
        "details": "Last Kiss Bearish | Zona=0.988 | Score=8/10 | R:R=1:2.32",
        "symbol": "AUDCAD=X",
        "display_name": "AUD/CAD",
        "timeframe": "4h"
      },
      {
        "strategy": "Moolah (Double Top)",
        "signal": "SHORT",
        "price": 1.05397,
        "zone": 1.0428,
        "first_touch": 1.05132,
        "second_touch": 1.05066,
        "candles_between": 42,
        "score": 8,
        "entry": 1.05397,
        "stop_loss": 1.0567,
        "take_profit": 1.0428,
        "rr_ratio": 4.09,
        "details": "Moolah | Zona=1.0428 | 1º=1.0513 2º=1.0507 (42 candles) | Score=8/10 | R:R=1:4.09",
        "symbol": "GBPCHF=X",
        "display_name": "GBP/CHF",
        "timeframe": "1d"
      },
      {
        "strategy": "EMA Pullback",
        "signal": "LONG",
        "rsi": 49.47,
        "price": 93.115,
        "ema21": 93.191,
        "ema50": 92.987,
        "score": 8,
        "entry": 93.114998,
        "stop_loss": 92.725046,
        "take_profit": 93.939334,
        "rr_ratio": 2.11,
        "details": "Pullback para EMA21 (0.1%) em uptrend | Score=8/10 | R:R=1:2.11",
        "symbol": "NZDJPY=X",
        "display_name": "NZD/JPY",
        "timeframe": "1d"
      },
      {
        "strategy": "Last Kiss",
        "signal": "SHORT",
        "price": 2.907,
        "zone": 2.9225,
        "score": 8,
        "entry": 2.907,
        "stop_loss": 3.01,
        "take_profit": 2.676,
        "rr_ratio": 2.24,
        "details": "Last Kiss Bearish | Zona=2.9225 | Score=8/10 | R:R=1:2.24",
        "symbol": "NG=F",
        "display_name": "Gás Natural",
        "timeframe": "1d"
      },
      {
        "strategy": "Last Kiss",
        "signal": "SHORT",
        "price": 10466.25977,
        "zone": 10480.17505,
        "score": 8,
        "entry": 10466.259766,
        "stop_loss": 10532.575924,
        "take_profit": 10286.945312,
        "rr_ratio": 2.7,
        "details": "Last Kiss Bearish | Zona=10480.175 | Score=8/10 | R:R=1:2.7",
        "symbol": "^FTSE",
        "display_name": "FTSE 100 (UK100)",
        "timeframe": "4h"
      }
    ]
  },
  {
    "timestamp": "2026-05-24T05:08:10.183658",
    "n_symbols": 47,
    "timeframes": [
      "4h",
      "1d"
    ],
    "elapsed": 23.0,
    "total_raw": 123,
    "total_approved": 13,
    "results": [
      {
        "strategy": "Wammie (Double Bottom)",
        "signal": "LONG",
        "price": 39.43,
        "zone": 38.71242,
        "first_touch": 38.68685,
        "second_touch": 38.7,
        "candles_between": 80,
        "score": 8,
        "entry": 39.43,
        "stop_loss": 38.518859,
        "take_profit": 41.94299,
        "rr_ratio": 2.76,
        "details": "Wammie | Zona=38.7124 | 1º=38.6869 2º=38.7 (80 candles) | Score=8/10 | R:R=1:2.76",
        "symbol": "ITUB4.SA",
        "display_name": "ITUB4 (Itaú)",
        "timeframe": "1d"
      },
      {
        "strategy": "Wammie (Double Bottom)",
        "signal": "LONG",
        "price": 17.62,
        "zone": 17.39137,
        "first_touch": 17.39452,
        "second_touch": 17.47,
        "candles_between": 93,
        "score": 8,
        "entry": 17.620001,
        "stop_loss": 17.304417,
        "take_profit": 18.305983,
        "rr_ratio": 2.17,
        "details": "Wammie | Zona=17.3914 | 1º=17.3945 2º=17.47 (93 candles) | Score=8/10 | R:R=1:2.17",
        "symbol": "BBDC4.SA",
        "display_name": "BBDC4 (Bradesco)",
        "timeframe": "1d"
      },
      {
        "strategy": "Last Kiss",
        "signal": "SHORT",
        "price": 17.62,
        "zone": 17.84488,
        "score": 8,
        "entry": 17.620001,
        "stop_loss": 17.9341,
        "take_profit": 16.97648,
        "rr_ratio": 2.05,
        "details": "Last Kiss Bearish | Zona=17.8449 | Score=8/10 | R:R=1:2.05",
        "symbol": "BBDC4.SA",
        "display_name": "BBDC4 (Bradesco)",
        "timeframe": "1d"
      },
      {
        "strategy": "Last Kiss",
        "signal": "SHORT",
        "price": 76673.99219,
        "zone": 77415.67708,
        "score": 9,
        "entry": 76673.992188,
        "stop_loss": 77802.755468,
        "take_profit": 74202.523438,
        "rr_ratio": 2.19,
        "details": "Last Kiss Bearish | Zona=77415.6771 | Score=9/10 | R:R=1:2.19",
        "symbol": "BTC-USD",
        "display_name": "Bitcoin (BTC/USD)",
        "timeframe": "4h"
      },
      {
        "strategy": "Wammie (Double Bottom)",
        "signal": "LONG",
        "price": 2117.6499,
        "zone": 2078.61621,
        "first_touch": 2061.46753,
        "second_touch": 2078.61621,
        "candles_between": 41,
        "score": 8,
        "entry": 2117.649902,
        "stop_loss": 2068.22313,
        "take_profit": 2221.223877,
        "rr_ratio": 2.1,
        "details": "Wammie | Zona=2078.6162 | 1º=2061.4675 2º=2078.6162 (41 candles) | Score=8/10 | R:R=1:2.1",
        "symbol": "ETH-USD",
        "display_name": "Ethereum (ETH/USD)",
        "timeframe": "1d"
      },
      {
        "strategy": "Last Kiss",
        "signal": "SHORT",
        "price": 85.73,
        "zone": 87.22,
        "score": 9,
        "entry": 85.730003,
        "stop_loss": 87.656099,
        "take_profit": 81.450001,
        "rr_ratio": 2.22,
        "details": "Last Kiss Bearish | Zona=87.22 | Score=9/10 | R:R=1:2.22",
        "symbol": "SOL-USD",
        "display_name": "Solana (SOL/USD)",
        "timeframe": "4h"
      },
      {
        "strategy": "Last Kiss",
        "signal": "SHORT",
        "price": 1.34329,
        "zone": 1.34734,
        "score": 9,
        "entry": 1.343292,
        "stop_loss": 1.354075,
        "take_profit": 1.319023,
        "rr_ratio": 2.25,
        "details": "Last Kiss Bearish | Zona=1.3473 | Score=9/10 | R:R=1:2.25",
        "symbol": "GBPUSD=X",
        "display_name": "GBP/USD",
        "timeframe": "4h"
      },
      {
        "strategy": "Last Kiss",
        "signal": "SHORT",
        "price": 0.71296,
        "zone": 0.7137,
        "score": 8,
        "entry": 0.712962,
        "stop_loss": 0.717264,
        "take_profit": 0.701592,
        "rr_ratio": 2.64,
        "details": "Last Kiss Bearish | Zona=0.7137 | Score=8/10 | R:R=1:2.64",
        "symbol": "AUDUSD=X",
        "display_name": "AUD/USD",
        "timeframe": "4h"
      },
      {
        "strategy": "Last Kiss",
        "signal": "SHORT",
        "price": 0.98399,
        "zone": 0.98802,
        "score": 8,
        "entry": 0.98399,
        "stop_loss": 0.992961,
        "take_profit": 0.963134,
        "rr_ratio": 2.32,
        "details": "Last Kiss Bearish | Zona=0.988 | Score=8/10 | R:R=1:2.32",
        "symbol": "AUDCAD=X",
        "display_name": "AUD/CAD",
        "timeframe": "4h"
      },
      {
        "strategy": "Moolah (Double Top)",
        "signal": "SHORT",
        "price": 1.05397,
        "zone": 1.0428,
        "first_touch": 1.05132,
        "second_touch": 1.05066,
        "candles_between": 42,
        "score": 8,
        "entry": 1.05397,
        "stop_loss": 1.0567,
        "take_profit": 1.0428,
        "rr_ratio": 4.09,
        "details": "Moolah | Zona=1.0428 | 1º=1.0513 2º=1.0507 (42 candles) | Score=8/10 | R:R=1:4.09",
        "symbol": "GBPCHF=X",
        "display_name": "GBP/CHF",
        "timeframe": "1d"
      },
      {
        "strategy": "EMA Pullback",
        "signal": "LONG",
        "rsi": 49.47,
        "price": 93.115,
        "ema21": 93.191,
        "ema50": 92.987,
        "score": 8,
        "entry": 93.114998,
        "stop_loss": 92.725046,
        "take_profit": 93.939334,
        "rr_ratio": 2.11,
        "details": "Pullback para EMA21 (0.1%) em uptrend | Score=8/10 | R:R=1:2.11",
        "symbol": "NZDJPY=X",
        "display_name": "NZD/JPY",
        "timeframe": "1d"
      },
      {
        "strategy": "Big Belt",
        "signal": "SHORT",
        "price": 3.021,
        "zone": 3.1275,
        "open": 3.133,
        "gap": 0.115,
        "room_to_left": 1,
        "score": 9,
        "entry": 3.021,
        "stop_loss": 3.148,
        "take_profit": 2.725,
        "rr_ratio": 2.33,
        "details": "Bearish Big Belt | Zona=3.1275 | Gap=↑0.115 | Score=9/10 | R:R=1:2.33",
        "symbol": "NG=F",
        "display_name": "Gás Natural",
        "timeframe": "1d"
      },
      {
        "strategy": "Last Kiss",
        "signal": "SHORT",
        "price": 10466.25977,
        "zone": 10480.17505,
        "score": 8,
        "entry": 10466.259766,
        "stop_loss": 10532.575924,
        "take_profit": 10286.945312,
        "rr_ratio": 2.7,
        "details": "Last Kiss Bearish | Zona=10480.175 | Score=8/10 | R:R=1:2.7",
        "symbol": "^FTSE",
        "display_name": "FTSE 100 (UK100)",
        "timeframe": "4h"
      }
    ]
  },
  {
    "timestamp": "2026-05-24T08:23:26.172549",
    "n_symbols": 47,
    "timeframes": [
      "4h",
      "1d"
    ],
    "elapsed": 27.8,
    "total_raw": 124,
    "total_approved": 11,
    "results": [
      {
        "strategy": "Wammie (Double Bottom)",
        "signal": "LONG",
        "price": 39.43,
        "zone": 38.71242,
        "first_touch": 38.68685,
        "second_touch": 38.7,
        "candles_between": 80,
        "score": 8,
        "entry": 39.43,
        "stop_loss": 38.518858,
        "take_profit": 41.94299,
        "rr_ratio": 2.76,
        "details": "Wammie | Zona=38.7124 | 1º=38.6869 2º=38.7 (80 candles) | Score=8/10 | R:R=1:2.76",
        "symbol": "ITUB4.SA",
        "display_name": "ITUB4 (Itaú)",
        "timeframe": "1d"
      },
      {
        "strategy": "Wammie (Double Bottom)",
        "signal": "LONG",
        "price": 17.62,
        "zone": 17.39137,
        "first_touch": 17.39452,
        "second_touch": 17.47,
        "candles_between": 93,
        "score": 8,
        "entry": 17.620001,
        "stop_loss": 17.304416,
        "take_profit": 18.305981,
        "rr_ratio": 2.17,
        "details": "Wammie | Zona=17.3914 | 1º=17.3945 2º=17.47 (93 candles) | Score=8/10 | R:R=1:2.17",
        "symbol": "BBDC4.SA",
        "display_name": "BBDC4 (Bradesco)",
        "timeframe": "1d"
      },
      {
        "strategy": "Last Kiss",
        "signal": "SHORT",
        "price": 17.62,
        "zone": 17.84487,
        "score": 8,
        "entry": 17.620001,
        "stop_loss": 17.934099,
        "take_profit": 16.976474,
        "rr_ratio": 2.05,
        "details": "Last Kiss Bearish | Zona=17.8449 | Score=8/10 | R:R=1:2.05",
        "symbol": "BBDC4.SA",
        "display_name": "BBDC4 (Bradesco)",
        "timeframe": "1d"
      },
      {
        "strategy": "Wammie (Double Bottom)",
        "signal": "LONG",
        "price": 76769.96094,
        "zone": 73918.23438,
        "first_touch": 73775.57031,
        "second_touch": 74255.23438,
        "candles_between": 33,
        "score": 9,
        "entry": 76769.960938,
        "stop_loss": 73548.643203,
        "take_profit": 83862.25,
        "rr_ratio": 2.2,
        "details": "Wammie | Zona=73918.2344 | 1º=73775.5703 2º=74255.2344 (33 candles) | Score=9/10 | R:R=1:2.2",
        "symbol": "BTC-USD",
        "display_name": "Bitcoin (BTC/USD)",
        "timeframe": "1d"
      },
      {
        "strategy": "Last Kiss",
        "signal": "SHORT",
        "price": 1.34329,
        "zone": 1.34734,
        "score": 9,
        "entry": 1.343292,
        "stop_loss": 1.354075,
        "take_profit": 1.319023,
        "rr_ratio": 2.25,
        "details": "Last Kiss Bearish | Zona=1.3473 | Score=9/10 | R:R=1:2.25",
        "symbol": "GBPUSD=X",
        "display_name": "GBP/USD",
        "timeframe": "4h"
      },
      {
        "strategy": "Last Kiss",
        "signal": "SHORT",
        "price": 0.71296,
        "zone": 0.7137,
        "score": 8,
        "entry": 0.712962,
        "stop_loss": 0.717264,
        "take_profit": 0.701592,
        "rr_ratio": 2.64,
        "details": "Last Kiss Bearish | Zona=0.7137 | Score=8/10 | R:R=1:2.64",
        "symbol": "AUDUSD=X",
        "display_name": "AUD/USD",
        "timeframe": "4h"
      },
      {
        "strategy": "Last Kiss",
        "signal": "SHORT",
        "price": 0.98399,
        "zone": 0.98802,
        "score": 8,
        "entry": 0.98399,
        "stop_loss": 0.992961,
        "take_profit": 0.963134,
        "rr_ratio": 2.32,
        "details": "Last Kiss Bearish | Zona=0.988 | Score=8/10 | R:R=1:2.32",
        "symbol": "AUDCAD=X",
        "display_name": "AUD/CAD",
        "timeframe": "4h"
      },
      {
        "strategy": "Moolah (Double Top)",
        "signal": "SHORT",
        "price": 1.05397,
        "zone": 1.0428,
        "first_touch": 1.05132,
        "second_touch": 1.05066,
        "candles_between": 42,
        "score": 8,
        "entry": 1.05397,
        "stop_loss": 1.0567,
        "take_profit": 1.0428,
        "rr_ratio": 4.09,
        "details": "Moolah | Zona=1.0428 | 1º=1.0513 2º=1.0507 (42 candles) | Score=8/10 | R:R=1:4.09",
        "symbol": "GBPCHF=X",
        "display_name": "GBP/CHF",
        "timeframe": "1d"
      },
      {
        "strategy": "EMA Pullback",
        "signal": "LONG",
        "rsi": 49.47,
        "price": 93.115,
        "ema21": 93.191,
        "ema50": 92.987,
        "score": 8,
        "entry": 93.114998,
        "stop_loss": 92.725046,
        "take_profit": 93.939334,
        "rr_ratio": 2.11,
        "details": "Pullback para EMA21 (0.1%) em uptrend | Score=8/10 | R:R=1:2.11",
        "symbol": "NZDJPY=X",
        "display_name": "NZD/JPY",
        "timeframe": "1d"
      },
      {
        "strategy": "Big Belt",
        "signal": "SHORT",
        "price": 3.021,
        "zone": 3.1275,
        "open": 3.133,
        "gap": 0.115,
        "room_to_left": 1,
        "score": 9,
        "entry": 3.021,
        "stop_loss": 3.148,
        "take_profit": 2.725,
        "rr_ratio": 2.33,
        "details": "Bearish Big Belt | Zona=3.1275 | Gap=↑0.115 | Score=9/10 | R:R=1:2.33",
        "symbol": "NG=F",
        "display_name": "Gás Natural",
        "timeframe": "1d"
      },
      {
        "strategy": "Last Kiss",
        "signal": "SHORT",
        "price": 10466.25977,
        "zone": 10480.17505,
        "score": 8,
        "entry": 10466.259766,
        "stop_loss": 10532.575924,
        "take_profit": 10286.945312,
        "rr_ratio": 2.7,
        "details": "Last Kiss Bearish | Zona=10480.175 | Score=8/10 | R:R=1:2.7",
        "symbol": "^FTSE",
        "display_name": "FTSE 100 (UK100)",
        "timeframe": "4h"
      }
    ]
  },
  {
    "timestamp": "2026-06-04T11:57:22.872067+01:00",
    "n_symbols": 43,
    "timeframes": [
      "4h",
      "1d"
    ],
    "elapsed": 15.4,
    "total_raw": 144,
    "total_approved": 19,
    "results": [
      {
        "strategy": "RSI Oversold",
        "signal": "LONG",
        "rsi": 16.75,
        "price": 62255.3203,
        "score": 8,
        "entry": 62255.320312,
        "stop_loss": 61351.628906,
        "take_profit": 65031.908203,
        "rr_ratio": 3.07,
        "details": "RSI=16.75 (abaixo de 35) | Score=8/10 | R:R=1:3.07",
        "symbol": "BTC-USD",
        "display_name": "Bitcoin (BTC/USD)",
        "timeframe": "1d"
      },
      {
        "strategy": "RSI Oversold",
        "signal": "LONG",
        "rsi": 19.2,
        "price": 67.66,
        "score": 8,
        "entry": 67.660004,
        "stop_loss": 67.489998,
        "take_profit": 72.230003,
        "rr_ratio": 26.88,
        "details": "RSI=19.2 (abaixo de 35) | Score=8/10 | R:R=1:26.88",
        "symbol": "SOL-USD",
        "display_name": "Solana (SOL/USD)",
        "timeframe": "4h"
      },
      {
        "strategy": "Big Belt",
        "signal": "LONG",
        "price": 1.34423,
        "zone": 1.33376,
        "open": 1.34198,
        "gap": 0.00345,
        "room_to_left": 0,
        "score": 9,
        "entry": 1.344231,
        "stop_loss": 1.327093,
        "take_profit": 1.384677,
        "rr_ratio": 2.36,
        "details": "Bullish Big Belt | Zona=1.3338 | Gap=↓0.0034 | Score=9/10 | R:R=1:2.36",
        "symbol": "GBPUSD=X",
        "display_name": "GBP/USD",
        "timeframe": "1d"
      },
      {
        "strategy": "EMA Pullback",
        "signal": "LONG",
        "rsi": 47.97,
        "price": 0.5632,
        "ema21": 0.5638,
        "ema50": 0.563,
        "score": 8,
        "entry": 0.56316,
        "stop_loss": 0.560952,
        "take_profit": 0.56787,
        "rr_ratio": 2.13,
        "details": "Pullback para EMA21 (0.1%) em uptrend | Score=8/10 | R:R=1:2.13",
        "symbol": "AUDCHF=X",
        "display_name": "AUD/CHF",
        "timeframe": "4h"
      },
      {
        "strategy": "Moolah (Double Top)",
        "signal": "SHORT",
        "price": 1.9794,
        "zone": 1.98362,
        "first_touch": 1.97653,
        "second_touch": 1.97557,
        "candles_between": 26,
        "score": 10,
        "entry": 1.9794,
        "stop_loss": 1.993534,
        "take_profit": 1.94433,
        "rr_ratio": 2.48,
        "details": "Moolah | Zona=1.9836 | 1º=1.9765 2º=1.9756 (26 candles) | Score=10/10 | R:R=1:2.48",
        "symbol": "EURNZD=X",
        "display_name": "EUR/NZD",
        "timeframe": "4h"
      },
      {
        "strategy": "Moolah (Double Top)",
        "signal": "SHORT",
        "price": 1.9794,
        "zone": 1.94853,
        "first_touch": 1.96615,
        "second_touch": 1.96048,
        "candles_between": 56,
        "score": 9,
        "entry": 1.9794,
        "stop_loss": 1.98007,
        "take_profit": 1.968876,
        "rr_ratio": 15.71,
        "details": "Moolah | Zona=1.9485 | 1º=1.9662 2º=1.9605 (56 candles) | Score=9/10 | R:R=1:15.71",
        "symbol": "EURNZD=X",
        "display_name": "EUR/NZD",
        "timeframe": "1d"
      },
      {
        "strategy": "Wammie (Double Bottom)",
        "signal": "LONG",
        "price": 2.28773,
        "zone": 2.3053,
        "first_touch": 2.28334,
        "second_touch": 2.28513,
        "candles_between": 32,
        "score": 8,
        "entry": 2.28773,
        "stop_loss": 2.28494,
        "take_profit": 2.302846,
        "rr_ratio": 5.42,
        "details": "Wammie | Zona=2.3053 | 1º=2.2833 2º=2.2851 (32 candles) | Score=8/10 | R:R=1:5.42",
        "symbol": "GBPNZD=X",
        "display_name": "GBP/NZD",
        "timeframe": "4h"
      },
      {
        "strategy": "Moolah (Double Top)",
        "signal": "SHORT",
        "price": 2.28773,
        "zone": 2.24376,
        "first_touch": 2.26388,
        "second_touch": 2.26189,
        "candles_between": 61,
        "score": 9,
        "entry": 2.28773,
        "stop_loss": 2.29026,
        "take_profit": 2.282343,
        "rr_ratio": 2.13,
        "details": "Moolah | Zona=2.2438 | 1º=2.2639 2º=2.2619 (61 candles) | Score=9/10 | R:R=1:2.13",
        "symbol": "GBPNZD=X",
        "display_name": "GBP/NZD",
        "timeframe": "1d"
      },
      {
        "strategy": "EMA Pullback",
        "signal": "LONG",
        "rsi": 44.83,
        "price": 0.8165,
        "ema21": 0.8179,
        "ema50": 0.8165,
        "score": 8,
        "entry": 0.81649,
        "stop_loss": 0.813824,
        "take_profit": 0.82191,
        "rr_ratio": 2.03,
        "details": "Pullback para EMA21 (0.2%) em uptrend | Score=8/10 | R:R=1:2.03",
        "symbol": "NZDCAD=X",
        "display_name": "NZD/CAD",
        "timeframe": "4h"
      },
      {
        "strategy": "Wammie (Double Bottom)",
        "signal": "LONG",
        "price": 0.81656,
        "zone": 0.82369,
        "first_touch": 0.81661,
        "second_touch": 0.8186,
        "candles_between": 65,
        "score": 8,
        "entry": 0.81656,
        "stop_loss": 0.81268,
        "take_profit": 0.824386,
        "rr_ratio": 2.02,
        "details": "Wammie | Zona=0.8237 | 1º=0.8166 2º=0.8186 (65 candles) | Score=8/10 | R:R=1:2.02",
        "symbol": "NZDCAD=X",
        "display_name": "NZD/CAD",
        "timeframe": "1d"
      },
      {
        "strategy": "Trendy Kangaroo",
        "signal": "LONG",
        "price": 0.46374,
        "trend": "Uptrend (EMA21 > EMA50)",
        "pause_range": "0.4634 - 0.4679",
        "tail_low": 0.46138,
        "score": 8,
        "entry": 0.46374,
        "stop_loss": 0.461083,
        "take_profit": 0.47071,
        "rr_ratio": 2.62,
        "details": "Trendy Kangaroo Bullish | Uptrend | Pausa=0.4634-0.4679 | Tail=0.4614 | Score=8/10 | R:R=1:2.62",
        "symbol": "NZDCHF=X",
        "display_name": "NZD/CHF",
        "timeframe": "1d"
      },
      {
        "strategy": "Moolah (Double Top)",
        "signal": "SHORT",
        "price": 0.58772,
        "zone": 0.58241,
        "first_touch": 0.58817,
        "second_touch": 0.58785,
        "candles_between": 33,
        "score": 8,
        "entry": 0.587717,
        "stop_loss": 0.587924,
        "take_profit": 0.585807,
        "rr_ratio": 9.21,
        "details": "Moolah | Zona=0.5824 | 1º=0.5882 2º=0.5879 (33 candles) | Score=8/10 | R:R=1:9.21",
        "symbol": "NZDUSD=X",
        "display_name": "NZD/USD",
        "timeframe": "4h"
      },
      {
        "strategy": "Big Belt",
        "signal": "LONG",
        "price": 0.58772,
        "zone": 0.58097,
        "open": 0.58627,
        "gap": 0.00598,
        "room_to_left": 0,
        "score": 9,
        "entry": 0.587717,
        "stop_loss": 0.578065,
        "take_profit": 0.607663,
        "rr_ratio": 2.07,
        "details": "Bullish Big Belt | Zona=0.581 | Gap=↓0.006 | Score=9/10 | R:R=1:2.07",
        "symbol": "NZDUSD=X",
        "display_name": "NZD/USD",
        "timeframe": "1d"
      },
      {
        "strategy": "Last Kiss",
        "signal": "LONG",
        "price": 0.58772,
        "zone": 0.58097,
        "score": 8,
        "entry": 0.587717,
        "stop_loss": 0.578065,
        "take_profit": 0.607663,
        "rr_ratio": 2.07,
        "details": "Last Kiss Bullish | Zona=0.581 | Score=8/10 | R:R=1:2.07",
        "symbol": "NZDUSD=X",
        "display_name": "NZD/USD",
        "timeframe": "1d"
      },
      {
        "strategy": "Wammie (Double Bottom)",
        "signal": "LONG",
        "price": 73.645,
        "zone": 73.26167,
        "first_touch": 73.03,
        "second_touch": 73.395,
        "candles_between": 25,
        "score": 8,
        "entry": 73.644997,
        "stop_loss": 72.89536,
        "take_profit": 75.264999,
        "rr_ratio": 2.16,
        "details": "Wammie | Zona=73.2617 | 1º=73.03 2º=73.395 (25 candles) | Score=8/10 | R:R=1:2.16",
        "symbol": "SI=F",
        "display_name": "Prata (XAG/USD)",
        "timeframe": "4h"
      },
      {
        "strategy": "Wammie (Double Bottom)",
        "signal": "LONG",
        "price": 3.247,
        "zone": 3.055,
        "first_touch": 3.045,
        "second_touch": 3.057,
        "candles_between": 47,
        "score": 8,
        "entry": 3.247,
        "stop_loss": 3.039725,
        "take_profit": 3.749,
        "rr_ratio": 2.42,
        "details": "Wammie | Zona=3.055 | 1º=3.045 2º=3.057 (47 candles) | Score=8/10 | R:R=1:2.42",
        "symbol": "NG=F",
        "display_name": "Gás Natural",
        "timeframe": "1d"
      },
      {
        "strategy": "Last Kiss",
        "signal": "SHORT",
        "price": 10244.41016,
        "zone": 10368.67101,
        "score": 8,
        "entry": 10244.410156,
        "stop_loss": 10420.514362,
        "take_profit": 9861.19043,
        "rr_ratio": 2.18,
        "details": "Last Kiss Bearish | Zona=10368.671 | Score=8/10 | R:R=1:2.18",
        "symbol": "^FTSE",
        "display_name": "FTSE 100 (UK100)",
        "timeframe": "4h"
      },
      {
        "strategy": "Last Kiss",
        "signal": "LONG",
        "price": 8686.09961,
        "zone": 8500.20019,
        "score": 9,
        "entry": 8686.099609,
        "stop_loss": 8457.699194,
        "take_profit": 9199.300293,
        "rr_ratio": 2.25,
        "details": "Last Kiss Bullish | Zona=8500.2002 | Score=9/10 | R:R=1:2.25",
        "symbol": "^AXJO",
        "display_name": "ASX 200 (AU200)",
        "timeframe": "4h"
      },
      {
        "strategy": "EMA Pullback",
        "signal": "LONG",
        "rsi": 49.7,
        "price": 18221.5,
        "ema21": 18250.7845,
        "ema50": 18130.8201,
        "score": 8,
        "entry": 18221.5,
        "stop_loss": 18159.530567,
        "take_profit": 18410.033203,
        "rr_ratio": 3.04,
        "details": "Pullback para EMA21 (0.2%) em uptrend | Score=8/10 | R:R=1:3.04",
        "symbol": "^IBEX",
        "display_name": "IBEX 35",
        "timeframe": "4h"
      }
    ]
  },
  {
    "timestamp": "2026-06-04T15:09:43.622317+01:00",
    "n_symbols": 43,
    "timeframes": [
      "4h",
      "1d"
    ],
    "elapsed": 16.7,
    "total_raw": 142,
    "total_approved": 18,
    "results": [
      {
        "strategy": "RSI Oversold",
        "signal": "LONG",
        "rsi": 19.6,
        "price": 64240.4102,
        "score": 8,
        "entry": 64240.410156,
        "stop_loss": 61351.628906,
        "take_profit": 70540.570312,
        "rr_ratio": 2.18,
        "details": "RSI=19.6 (abaixo de 35) | Score=8/10 | R:R=1:2.18",
        "symbol": "BTC-USD",
        "display_name": "Bitcoin (BTC/USD)",
        "timeframe": "1d"
      },
      {
        "strategy": "RSI Oversold",
        "signal": "LONG",
        "rsi": 18.85,
        "price": 1786.2,
        "score": 8,
        "entry": 1786.199951,
        "stop_loss": 1717.80249,
        "take_profit": 1939.528687,
        "rr_ratio": 2.24,
        "details": "RSI=18.85 (abaixo de 35) | Score=8/10 | R:R=1:2.24",
        "symbol": "ETH-USD",
        "display_name": "Ethereum (ETH/USD)",
        "timeframe": "1d"
      },
      {
        "strategy": "Trendy Kangaroo",
        "signal": "SHORT",
        "price": 1.16374,
        "trend": "Downtrend (EMA21 < EMA50)",
        "pause_range": "1.1602 - 1.1637",
        "tail_high": 1.16482,
        "score": 9,
        "entry": 1.163738,
        "stop_loss": 1.169557,
        "take_profit": 1.147682,
        "rr_ratio": 2.76,
        "details": "Trendy Kangaroo Bearish | Downtrend | Pausa=1.1602-1.1637 | Tail=1.1648 | Score=9/10 | R:R=1:2.76",
        "symbol": "EURUSD=X",
        "display_name": "EUR/USD",
        "timeframe": "4h"
      },
      {
        "strategy": "EMA Pullback",
        "signal": "LONG",
        "rsi": 49.33,
        "price": 1.2135,
        "ema21": 1.2142,
        "ema50": 1.2106,
        "score": 8,
        "entry": 1.21348,
        "stop_loss": 1.208093,
        "take_profit": 1.22801,
        "rr_ratio": 2.7,
        "details": "Pullback para EMA21 (0.1%) em uptrend | Score=8/10 | R:R=1:2.7",
        "symbol": "AUDNZD=X",
        "display_name": "AUD/NZD",
        "timeframe": "1d"
      },
      {
        "strategy": "Trendy Kangaroo",
        "signal": "LONG",
        "price": 115.144,
        "trend": "Uptrend (EMA21 > EMA50)",
        "pause_range": "115.11 - 115.663",
        "tail_low": 114.805,
        "score": 9,
        "entry": 115.143997,
        "stop_loss": 114.534451,
        "take_profit": 117.269333,
        "rr_ratio": 3.49,
        "details": "Trendy Kangaroo Bullish | Uptrend | Pausa=115.11-115.663 | Tail=114.805 | Score=9/10 | R:R=1:3.49",
        "symbol": "CADJPY=X",
        "display_name": "CAD/JPY",
        "timeframe": "1d"
      },
      {
        "strategy": "Moolah (Double Top)",
        "signal": "SHORT",
        "price": 1.97729,
        "zone": 1.94853,
        "first_touch": 1.96615,
        "second_touch": 1.96048,
        "candles_between": 56,
        "score": 9,
        "entry": 1.97729,
        "stop_loss": 1.98007,
        "take_profit": 1.968876,
        "rr_ratio": 3.03,
        "details": "Moolah | Zona=1.9485 | 1º=1.9662 2º=1.9605 (56 candles) | Score=9/10 | R:R=1:3.03",
        "symbol": "EURNZD=X",
        "display_name": "EUR/NZD",
        "timeframe": "1d"
      },
      {
        "strategy": "Wammie (Double Bottom)",
        "signal": "LONG",
        "price": 2.28559,
        "zone": 2.3053,
        "first_touch": 2.28334,
        "second_touch": 2.28513,
        "candles_between": 32,
        "score": 8,
        "entry": 2.28559,
        "stop_loss": 2.28329,
        "take_profit": 2.291508,
        "rr_ratio": 2.57,
        "details": "Wammie | Zona=2.3053 | 1º=2.2833 2º=2.2851 (32 candles) | Score=8/10 | R:R=1:2.57",
        "symbol": "GBPNZD=X",
        "display_name": "GBP/NZD",
        "timeframe": "4h"
      },
      {
        "strategy": "Moolah (Double Top)",
        "signal": "SHORT",
        "price": 2.28559,
        "zone": 2.24376,
        "first_touch": 2.26388,
        "second_touch": 2.26189,
        "candles_between": 61,
        "score": 9,
        "entry": 2.28559,
        "stop_loss": 2.29026,
        "take_profit": 2.276167,
        "rr_ratio": 2.02,
        "details": "Moolah | Zona=2.2438 | 1º=2.2639 2º=2.2619 (61 candles) | Score=9/10 | R:R=1:2.02",
        "symbol": "GBPNZD=X",
        "display_name": "GBP/NZD",
        "timeframe": "1d"
      },
      {
        "strategy": "EMA Pullback",
        "signal": "LONG",
        "rsi": 46.84,
        "price": 0.817,
        "ema21": 0.8178,
        "ema50": 0.8165,
        "score": 8,
        "entry": 0.81699,
        "stop_loss": 0.813745,
        "take_profit": 0.82719,
        "rr_ratio": 3.14,
        "details": "Pullback para EMA21 (0.1%) em uptrend | Score=8/10 | R:R=1:3.14",
        "symbol": "NZDCAD=X",
        "display_name": "NZD/CAD",
        "timeframe": "4h"
      },
      {
        "strategy": "Wammie (Double Bottom)",
        "signal": "LONG",
        "price": 0.81699,
        "zone": 0.82369,
        "first_touch": 0.81661,
        "second_touch": 0.8186,
        "candles_between": 65,
        "score": 8,
        "entry": 0.81699,
        "stop_loss": 0.81268,
        "take_profit": 0.827107,
        "rr_ratio": 2.35,
        "details": "Wammie | Zona=0.8237 | 1º=0.8166 2º=0.8186 (65 candles) | Score=8/10 | R:R=1:2.35",
        "symbol": "NZDCAD=X",
        "display_name": "NZD/CAD",
        "timeframe": "1d"
      },
      {
        "strategy": "Moolah (Double Top)",
        "signal": "SHORT",
        "price": 0.58851,
        "zone": 0.58241,
        "first_touch": 0.58817,
        "second_touch": 0.58785,
        "candles_between": 33,
        "score": 8,
        "entry": 0.588512,
        "stop_loss": 0.588824,
        "take_profit": 0.587829,
        "rr_ratio": 2.19,
        "details": "Moolah | Zona=0.5824 | 1º=0.5882 2º=0.5879 (33 candles) | Score=8/10 | R:R=1:2.19",
        "symbol": "NZDUSD=X",
        "display_name": "NZD/USD",
        "timeframe": "4h"
      },
      {
        "strategy": "Big Belt",
        "signal": "LONG",
        "price": 0.58851,
        "zone": 0.58097,
        "open": 0.58627,
        "gap": 0.00598,
        "room_to_left": 0,
        "score": 9,
        "entry": 0.588512,
        "stop_loss": 0.578065,
        "take_profit": 0.610724,
        "rr_ratio": 2.13,
        "details": "Bullish Big Belt | Zona=0.581 | Gap=↓0.006 | Score=9/10 | R:R=1:2.13",
        "symbol": "NZDUSD=X",
        "display_name": "NZD/USD",
        "timeframe": "1d"
      },
      {
        "strategy": "Last Kiss",
        "signal": "LONG",
        "price": 0.58851,
        "zone": 0.58097,
        "score": 8,
        "entry": 0.588512,
        "stop_loss": 0.578065,
        "take_profit": 0.610724,
        "rr_ratio": 2.13,
        "details": "Last Kiss Bullish | Zona=0.581 | Score=8/10 | R:R=1:2.13",
        "symbol": "NZDUSD=X",
        "display_name": "NZD/USD",
        "timeframe": "1d"
      },
      {
        "strategy": "Wammie (Double Bottom)",
        "signal": "LONG",
        "price": 3.334,
        "zone": 3.055,
        "first_touch": 3.045,
        "second_touch": 3.057,
        "candles_between": 47,
        "score": 8,
        "entry": 3.334,
        "stop_loss": 3.039725,
        "take_profit": 4.148,
        "rr_ratio": 2.77,
        "details": "Wammie | Zona=3.055 | 1º=3.045 2º=3.057 (47 candles) | Score=8/10 | R:R=1:2.77",
        "symbol": "NG=F",
        "display_name": "Gás Natural",
        "timeframe": "1d"
      },
      {
        "strategy": "Last Kiss",
        "signal": "LONG",
        "price": 3.334,
        "zone": 2.676,
        "score": 8,
        "entry": 3.334,
        "stop_loss": 2.66262,
        "take_profit": 4.6815,
        "rr_ratio": 2.01,
        "details": "Last Kiss Bullish | Zona=2.676 | Score=8/10 | R:R=1:2.01",
        "symbol": "NG=F",
        "display_name": "Gás Natural",
        "timeframe": "1d"
      },
      {
        "strategy": "EMA Pullback",
        "signal": "LONG",
        "rsi": 49.82,
        "price": 24961.8691,
        "ema21": 24987.8207,
        "ema50": 24833.7552,
        "score": 8,
        "entry": 24961.869141,
        "stop_loss": 24862.881588,
        "take_profit": 25212.605469,
        "rr_ratio": 2.53,
        "details": "Pullback para EMA21 (0.1%) em uptrend | Score=8/10 | R:R=1:2.53",
        "symbol": "^GDAXI",
        "display_name": "DAX (DE30)",
        "timeframe": "4h"
      },
      {
        "strategy": "Last Kiss",
        "signal": "LONG",
        "price": 10341.78027,
        "zone": 10205.13346,
        "score": 8,
        "entry": 10341.780273,
        "stop_loss": 10154.107797,
        "take_profit": 10745.799805,
        "rr_ratio": 2.15,
        "details": "Last Kiss Bullish | Zona=10205.1335 | Score=8/10 | R:R=1:2.15",
        "symbol": "^FTSE",
        "display_name": "FTSE 100 (UK100)",
        "timeframe": "1d"
      },
      {
        "strategy": "Last Kiss",
        "signal": "LONG",
        "price": 8686.09961,
        "zone": 8500.20019,
        "score": 9,
        "entry": 8686.099609,
        "stop_loss": 8457.699194,
        "take_profit": 9199.300293,
        "rr_ratio": 2.25,
        "details": "Last Kiss Bullish | Zona=8500.2002 | Score=9/10 | R:R=1:2.25",
        "symbol": "^AXJO",
        "display_name": "ASX 200 (AU200)",
        "timeframe": "4h"
      }
    ]
  },
  {
    "timestamp": "2026-06-04T18:49:54.473289+01:00",
    "n_symbols": 43,
    "timeframes": [
      "4h",
      "1d"
    ],
    "elapsed": 15.4,
    "total_raw": 139,
    "total_approved": 13,
    "results": [
      {
        "strategy": "RSI Oversold",
        "signal": "LONG",
        "rsi": 17.45,
        "price": 62993.7383,
        "score": 8,
        "entry": 62993.738281,
        "stop_loss": 61351.628906,
        "take_profit": 67372.875,
        "rr_ratio": 2.67,
        "details": "RSI=17.45 (abaixo de 35) | Score=8/10 | R:R=1:2.67",
        "symbol": "BTC-USD",
        "display_name": "Bitcoin (BTC/USD)",
        "timeframe": "1d"
      },
      {
        "strategy": "Last Kiss",
        "signal": "SHORT",
        "price": 1.34288,
        "zone": 1.34719,
        "score": 8,
        "entry": 1.342877,
        "stop_loss": 1.353922,
        "take_profit": 1.319023,
        "rr_ratio": 2.16,
        "details": "Last Kiss Bearish | Zona=1.3472 | Score=8/10 | R:R=1:2.16",
        "symbol": "GBPUSD=X",
        "display_name": "GBP/USD",
        "timeframe": "4h"
      },
      {
        "strategy": "Trendy Kangaroo",
        "signal": "LONG",
        "price": 115.096,
        "trend": "Uptrend (EMA21 > EMA50)",
        "pause_range": "115.11 - 115.663",
        "tail_low": 114.805,
        "score": 8,
        "entry": 115.096001,
        "stop_loss": 114.534451,
        "take_profit": 116.247498,
        "rr_ratio": 2.05,
        "details": "Trendy Kangaroo Bullish | Uptrend | Pausa=115.11-115.663 | Tail=114.805 | Score=8/10 | R:R=1:2.05",
        "symbol": "CADJPY=X",
        "display_name": "CAD/JPY",
        "timeframe": "1d"
      },
      {
        "strategy": "Last Kiss",
        "signal": "SHORT",
        "price": 202.741,
        "zone": 203.8935,
        "score": 8,
        "entry": 202.740997,
        "stop_loss": 204.912969,
        "take_profit": 197.958504,
        "rr_ratio": 2.2,
        "details": "Last Kiss Bearish | Zona=203.8935 | Score=8/10 | R:R=1:2.2",
        "symbol": "CHFJPY=X",
        "display_name": "CHF/JPY",
        "timeframe": "4h"
      },
      {
        "strategy": "Big Belt",
        "signal": "LONG",
        "price": 1.97794,
        "zone": 1.9655,
        "open": 1.97615,
        "gap": 0.00144,
        "room_to_left": 0,
        "score": 8,
        "entry": 1.97794,
        "stop_loss": 1.955675,
        "take_profit": 2.03118,
        "rr_ratio": 2.39,
        "details": "Bullish Big Belt | Zona=1.9655 | Gap=↓0.0014 | Score=8/10 | R:R=1:2.39",
        "symbol": "EURNZD=X",
        "display_name": "EUR/NZD",
        "timeframe": "4h"
      },
      {
        "strategy": "Moolah (Double Top)",
        "signal": "SHORT",
        "price": 1.97794,
        "zone": 1.94853,
        "first_touch": 1.96615,
        "second_touch": 1.96048,
        "candles_between": 56,
        "score": 9,
        "entry": 1.97794,
        "stop_loss": 1.98007,
        "take_profit": 1.968876,
        "rr_ratio": 4.26,
        "details": "Moolah | Zona=1.9485 | 1º=1.9662 2º=1.9605 (56 candles) | Score=9/10 | R:R=1:4.26",
        "symbol": "EURNZD=X",
        "display_name": "EUR/NZD",
        "timeframe": "1d"
      },
      {
        "strategy": "Moolah (Double Top)",
        "signal": "SHORT",
        "price": 2.2858,
        "zone": 2.24376,
        "first_touch": 2.26388,
        "second_touch": 2.26189,
        "candles_between": 61,
        "score": 9,
        "entry": 2.2858,
        "stop_loss": 2.29026,
        "take_profit": 2.276167,
        "rr_ratio": 2.16,
        "details": "Moolah | Zona=2.2438 | 1º=2.2639 2º=2.2619 (61 candles) | Score=9/10 | R:R=1:2.16",
        "symbol": "GBPNZD=X",
        "display_name": "GBP/NZD",
        "timeframe": "1d"
      },
      {
        "strategy": "Wammie (Double Bottom)",
        "signal": "LONG",
        "price": 0.81641,
        "zone": 0.82369,
        "first_touch": 0.81661,
        "second_touch": 0.8186,
        "candles_between": 65,
        "score": 8,
        "entry": 0.81641,
        "stop_loss": 0.81268,
        "take_profit": 0.824386,
        "rr_ratio": 2.14,
        "details": "Wammie | Zona=0.8237 | 1º=0.8166 2º=0.8186 (65 candles) | Score=8/10 | R:R=1:2.14",
        "symbol": "NZDCAD=X",
        "display_name": "NZD/CAD",
        "timeframe": "1d"
      },
      {
        "strategy": "Last Kiss",
        "signal": "SHORT",
        "price": 0.58761,
        "zone": 0.59239,
        "score": 8,
        "entry": 0.587613,
        "stop_loss": 0.59535,
        "take_profit": 0.569688,
        "rr_ratio": 2.32,
        "details": "Last Kiss Bearish | Zona=0.5924 | Score=8/10 | R:R=1:2.32",
        "symbol": "NZDUSD=X",
        "display_name": "NZD/USD",
        "timeframe": "4h"
      },
      {
        "strategy": "Wammie (Double Bottom)",
        "signal": "LONG",
        "price": 3.349,
        "zone": 3.055,
        "first_touch": 3.045,
        "second_touch": 3.057,
        "candles_between": 47,
        "score": 8,
        "entry": 3.349,
        "stop_loss": 3.039725,
        "take_profit": 4.148,
        "rr_ratio": 2.58,
        "details": "Wammie | Zona=3.055 | 1º=3.045 2º=3.057 (47 candles) | Score=8/10 | R:R=1:2.58",
        "symbol": "NG=F",
        "display_name": "Gás Natural",
        "timeframe": "1d"
      },
      {
        "strategy": "EMA Pullback",
        "signal": "LONG",
        "rsi": 49.37,
        "price": 24944.9492,
        "ema21": 24978.6035,
        "ema50": 24835.6905,
        "score": 8,
        "entry": 24944.949219,
        "stop_loss": 24853.710503,
        "take_profit": 25143.906901,
        "rr_ratio": 2.18,
        "details": "Pullback para EMA21 (0.1%) em uptrend | Score=8/10 | R:R=1:2.18",
        "symbol": "^GDAXI",
        "display_name": "DAX (DE30)",
        "timeframe": "4h"
      },
      {
        "strategy": "Last Kiss",
        "signal": "LONG",
        "price": 10360.32031,
        "zone": 10205.13346,
        "score": 9,
        "entry": 10360.320312,
        "stop_loss": 10154.107797,
        "take_profit": 10934.900391,
        "rr_ratio": 2.79,
        "details": "Last Kiss Bullish | Zona=10205.1335 | Score=9/10 | R:R=1:2.79",
        "symbol": "^FTSE",
        "display_name": "FTSE 100 (UK100)",
        "timeframe": "1d"
      },
      {
        "strategy": "Last Kiss",
        "signal": "LONG",
        "price": 8686.09961,
        "zone": 8500.20019,
        "score": 9,
        "entry": 8686.099609,
        "stop_loss": 8457.699194,
        "take_profit": 9199.300293,
        "rr_ratio": 2.25,
        "details": "Last Kiss Bullish | Zona=8500.2002 | Score=9/10 | R:R=1:2.25",
        "symbol": "^AXJO",
        "display_name": "ASX 200 (AU200)",
        "timeframe": "4h"
      }
    ]
  },
  {
    "timestamp": "2026-06-04T22:01:26.855420+01:00",
    "n_symbols": 43,
    "timeframes": [
      "4h",
      "1d"
    ],
    "elapsed": 15.3,
    "total_raw": 125,
    "total_approved": 15,
    "results": [
      {
        "strategy": "RSI Oversold",
        "signal": "LONG",
        "rsi": 18.08,
        "price": 63611.5312,
        "score": 8,
        "entry": 63611.53125,
        "stop_loss": 61351.628906,
        "take_profit": 68657.703125,
        "rr_ratio": 2.23,
        "details": "RSI=18.08 (abaixo de 35) | Score=8/10 | R:R=1:2.23",
        "symbol": "BTC-USD",
        "display_name": "Bitcoin (BTC/USD)",
        "timeframe": "1d"
      },
      {
        "strategy": "EMA Pullback",
        "signal": "LONG",
        "rsi": 47.39,
        "price": 0.714,
        "ema21": 0.7161,
        "ema50": 0.7128,
        "score": 8,
        "entry": 0.71398,
        "stop_loss": 0.712543,
        "take_profit": 0.719388,
        "rr_ratio": 3.76,
        "details": "Pullback para EMA21 (0.3%) em uptrend | Score=8/10 | R:R=1:3.76",
        "symbol": "AUDUSD=X",
        "display_name": "AUD/USD",
        "timeframe": "1d"
      },
      {
        "strategy": "Big Belt",
        "signal": "SHORT",
        "price": 0.91605,
        "zone": 0.91048,
        "open": 0.91845,
        "gap": 0.00237,
        "room_to_left": 0,
        "score": 9,
        "entry": 0.91605,
        "stop_loss": 0.91902,
        "take_profit": 0.90339,
        "rr_ratio": 4.26,
        "details": "Bearish Big Belt | Zona=0.9105 | Gap=↑0.0024 | Score=9/10 | R:R=1:4.26",
        "symbol": "EURCHF=X",
        "display_name": "EUR/CHF",
        "timeframe": "1d"
      },
      {
        "strategy": "Moolah (Double Top)",
        "signal": "SHORT",
        "price": 1.97824,
        "zone": 1.94853,
        "first_touch": 1.96615,
        "second_touch": 1.96048,
        "candles_between": 56,
        "score": 9,
        "entry": 1.97824,
        "stop_loss": 1.98007,
        "take_profit": 1.968876,
        "rr_ratio": 5.12,
        "details": "Moolah | Zona=1.9485 | 1º=1.9662 2º=1.9605 (56 candles) | Score=9/10 | R:R=1:5.12",
        "symbol": "EURNZD=X",
        "display_name": "EUR/NZD",
        "timeframe": "1d"
      },
      {
        "strategy": "Moolah (Double Top)",
        "signal": "SHORT",
        "price": 2.28618,
        "zone": 2.24376,
        "first_touch": 2.26388,
        "second_touch": 2.26189,
        "candles_between": 61,
        "score": 9,
        "entry": 2.28618,
        "stop_loss": 2.29026,
        "take_profit": 2.276167,
        "rr_ratio": 2.45,
        "details": "Moolah | Zona=2.2438 | 1º=2.2639 2º=2.2619 (61 candles) | Score=9/10 | R:R=1:2.45",
        "symbol": "GBPNZD=X",
        "display_name": "GBP/NZD",
        "timeframe": "1d"
      },
      {
        "strategy": "Wammie (Double Bottom)",
        "signal": "LONG",
        "price": 0.81532,
        "zone": 0.82369,
        "first_touch": 0.81661,
        "second_touch": 0.8186,
        "candles_between": 65,
        "score": 8,
        "entry": 0.81532,
        "stop_loss": 0.81268,
        "take_profit": 0.823686,
        "rr_ratio": 3.17,
        "details": "Wammie | Zona=0.8237 | 1º=0.8166 2º=0.8186 (65 candles) | Score=8/10 | R:R=1:3.17",
        "symbol": "NZDCAD=X",
        "display_name": "NZD/CAD",
        "timeframe": "1d"
      },
      {
        "strategy": "EMA Pullback",
        "signal": "LONG",
        "rsi": 49.9,
        "price": 0.4626,
        "ema21": 0.4629,
        "ema50": 0.4619,
        "score": 8,
        "entry": 0.46256,
        "stop_loss": 0.460593,
        "take_profit": 0.46812,
        "rr_ratio": 2.83,
        "details": "Pullback para EMA21 (0.1%) em uptrend | Score=8/10 | R:R=1:2.83",
        "symbol": "NZDCHF=X",
        "display_name": "NZD/CHF",
        "timeframe": "1d"
      },
      {
        "strategy": "Wammie (Double Bottom)",
        "signal": "LONG",
        "price": 93.872,
        "zone": 94.822,
        "first_touch": 93.988,
        "second_touch": 94.65,
        "candles_between": 27,
        "score": 8,
        "entry": 93.872002,
        "stop_loss": 93.698997,
        "take_profit": 94.295998,
        "rr_ratio": 2.45,
        "details": "Wammie | Zona=94.822 | 1º=93.988 2º=94.65 (27 candles) | Score=8/10 | R:R=1:2.45",
        "symbol": "NZDJPY=X",
        "display_name": "NZD/JPY",
        "timeframe": "1d"
      },
      {
        "strategy": "Last Kiss",
        "signal": "SHORT",
        "price": 4502.7002,
        "zone": 4517.79997,
        "score": 8,
        "entry": 4502.700195,
        "stop_loss": 4540.388967,
        "take_profit": 4395.600098,
        "rr_ratio": 2.84,
        "details": "Last Kiss Bearish | Zona=4517.8 | Score=8/10 | R:R=1:2.84",
        "symbol": "GC=F",
        "display_name": "Ouro (XAU/USD)",
        "timeframe": "4h"
      },
      {
        "strategy": "Last Kiss",
        "signal": "SHORT",
        "price": 74.135,
        "zone": 74.76,
        "score": 8,
        "entry": 74.135002,
        "stop_loss": 75.133799,
        "take_profit": 71.8675,
        "rr_ratio": 2.27,
        "details": "Last Kiss Bearish | Zona=74.76 | Score=8/10 | R:R=1:2.27",
        "symbol": "SI=F",
        "display_name": "Prata (XAG/USD)",
        "timeframe": "4h"
      },
      {
        "strategy": "Wammie (Double Bottom)",
        "signal": "LONG",
        "price": 3.355,
        "zone": 3.055,
        "first_touch": 3.045,
        "second_touch": 3.057,
        "candles_between": 47,
        "score": 8,
        "entry": 3.355,
        "stop_loss": 3.039725,
        "take_profit": 4.148,
        "rr_ratio": 2.52,
        "details": "Wammie | Zona=3.055 | 1º=3.045 2º=3.057 (47 candles) | Score=8/10 | R:R=1:2.52",
        "symbol": "NG=F",
        "display_name": "Gás Natural",
        "timeframe": "1d"
      },
      {
        "strategy": "EMA Pullback",
        "signal": "LONG",
        "rsi": 49.37,
        "price": 24944.9492,
        "ema21": 24978.6035,
        "ema50": 24835.6905,
        "score": 8,
        "entry": 24944.949219,
        "stop_loss": 24853.710503,
        "take_profit": 25143.906901,
        "rr_ratio": 2.18,
        "details": "Pullback para EMA21 (0.1%) em uptrend | Score=8/10 | R:R=1:2.18",
        "symbol": "^GDAXI",
        "display_name": "DAX (DE30)",
        "timeframe": "4h"
      },
      {
        "strategy": "Last Kiss",
        "signal": "LONG",
        "price": 10360.32031,
        "zone": 10205.13346,
        "score": 9,
        "entry": 10360.320312,
        "stop_loss": 10154.107797,
        "take_profit": 10934.900391,
        "rr_ratio": 2.79,
        "details": "Last Kiss Bullish | Zona=10205.1335 | Score=9/10 | R:R=1:2.79",
        "symbol": "^FTSE",
        "display_name": "FTSE 100 (UK100)",
        "timeframe": "1d"
      },
      {
        "strategy": "Last Kiss",
        "signal": "SHORT",
        "price": 7584.81982,
        "zone": 7620.8999,
        "score": 8,
        "entry": 7584.819824,
        "stop_loss": 7659.004402,
        "take_profit": 7428.970215,
        "rr_ratio": 2.1,
        "details": "Last Kiss Bearish | Zona=7620.8999 | Score=8/10 | R:R=1:2.1",
        "symbol": "^GSPC",
        "display_name": "S&P 500 (US500)",
        "timeframe": "4h"
      },
      {
        "strategy": "Last Kiss",
        "signal": "LONG",
        "price": 8686.09961,
        "zone": 8500.20019,
        "score": 9,
        "entry": 8686.099609,
        "stop_loss": 8457.699194,
        "take_profit": 9199.300293,
        "rr_ratio": 2.25,
        "details": "Last Kiss Bullish | Zona=8500.2002 | Score=9/10 | R:R=1:2.25",
        "symbol": "^AXJO",
        "display_name": "ASX 200 (AU200)",
        "timeframe": "4h"
      }
    ]
  }
]